{
  "job_id": "demo-topcoder-star",
  "input_uri": "demo-output/Profile_Intro_Video_Generated.mp4",
  "outputs": {
    "landscape": "demo-output/after/profile_landscape.mp4",
    "vertical": "demo-output/after/profile_vertical.mp4"
  },
  "captions": {
    "srt": "demo-output/after/captions.srt",
    "ass": "demo-output/after/captions.ass"
  },
  "manifest_path": "demo-output/after/manifest.json",
  "duration_seconds": 29.0,
  "estimated_cost_usd": 0.0017,
  "output_file_sizes_bytes": {
    "landscape": 5153086,
    "vertical": 6991316
  },
  "timings": {
    "probe_seconds": 0.066,
    "audio_seconds": 3.534,
    "caption_seconds": 0.002,
    "render_seconds": 32.187
  },
  "adapters": {
    "transcription": "fallback-scripted",
    "renderer": "ffmpeg-libx264-libass",
    "audio": "ffmpeg-afftdn-loudnorm-sidechaincompress"
  },
  "warnings": []
}